{
  "translation": {
    "cellHandling": "scCellHandling",
  	"libraryConstruction": "rnaLibraryConstruction",
  	"projectId": "projectId",
  	"bodyPart": "samples.sampleBodyPart",
  	"spikeIn": "rnaSpikeIn",
  	"pairedEnds": "pairedEnds",
  	"instrumentPlatform": "seqInstrumentPlatform",
  	"sampleSpecies": "samples.sampleSpecies",
    "fileFormat": "files.format",
    "computationalMethod": "analysisComputationalMethod",
    "bundleType": "bundles.type",
    "fileSize": "files.size",
    "projectCode": "projectId",
    "sampleId": "samples.sampleId",
    "File ID:Version": "es_uuid",
    "Assay Id": "assayId",
    "Analysis Id": "analysisId",
    "Project Id": "projectId"
  },
  "autocomplete-translation": {
    "ES_FILE_INDEX": {
      "centerName": "center_name",
      "workFlow": "workflow",
      "program": "program",
      "projectCode": "project",
      "analysisType": "analysis_type",
      "fileFormat": "file_type",
      "fileSize": "fileSize",
      "specimenType": "specimen_type",
      "software": "software",
      "fileId": "file_id",
      "id": "file_id",
      "donorId": "donor",
      "donor": "donor",
      "primarySite": "submitterDonorPrimarySite",
      "Program": "program",
      "Project": "project",
      "Center Name": "center_name",
      "Submitter Donor ID": "submittedDonorId",
      "Donor UUID": "donor",
      "Submitter Donor Primary Site": "submitterDonorPrimarySite",
      "Submitter Specimen ID": "submittedSpecimenId",
      "Specimen UUID": "specimenUUID",
      "Submitter Specimen Type": "specimen_type",
      "Submitter Experimental Design": "experimentalStrategy",
      "Submitter Sample ID": "submittedSampleId",
      "Sample UUID": "sampleId",
      "Analysis Type": "analysis_type",
      "Workflow Name": "software",
      "Workflow Version": "workflowVersion",
      "File Type": "file_type",
      "File Path": "title",
      "Upload File ID": "file_id",
      "Data Bundle UUID": "repoDataBundleId",
      "Metadata.json": "metadataJson"
    },
    "ES_DONOR_INDEX": {
      "donor": "donor_uuid"
    }
  },
  "manifest": [
    "File ID:Version",
    "Assay Id",
    "Analysis Id",
    "Project Id"
  ],
  "facets": [
    "cellHandling",
  	"libraryConstruction",
  	"projectId",
  	"bodyPart",
  	"spikeIn",
  	"pairedEnds",
  	"instrumentPlatform",
  	"sampleSpecies",
  	"fileFormat",
  	"computationalMethod",
    "bundleType"
  ]
}
